ruth_tts_transformer/__init__.py
ruth_tts_transformer/api.py
ruth_tts_transformer/parser.py
ruth_tts_transformer/server.py
ruth_tts_transformer/models/__init__.py
ruth_tts_transformer/models/arch_util.py
ruth_tts_transformer/models/autoregressive.py
ruth_tts_transformer/models/classifier.py
ruth_tts_transformer/models/clvp.py
ruth_tts_transformer/models/cvvp.py
ruth_tts_transformer/models/diffusion_decoder.py
ruth_tts_transformer/models/random_latent_generator.py
ruth_tts_transformer/models/transformer.py
ruth_tts_transformer/models/vocoder.py
ruth_tts_transformer/models/xtransformers.py
ruth_tts_transformer/utils/__init__.py
ruth_tts_transformer/utils/audio.py
ruth_tts_transformer/utils/diffusion.py
ruth_tts_transformer/utils/stft.py
ruth_tts_transformer/utils/text.py
ruth_tts_transformer/utils/tokenizer.py
ruth_tts_transformer/utils/try.py
ruth_tts_transformer/utils/typical_sampling.py
ruth_tts_transformer/utils/wav2vec_alignment.py
ruth_text_to_speech-0.0.39.dist-info/METADATA
ruth_text_to_speech-0.0.39.dist-info/WHEEL
ruth_text_to_speech-0.0.39.dist-info/entry_points.txt
ruth_text_to_speech-0.0.39.dist-info/top_level.txt
ruth_text_to_speech-0.0.39.dist-info/RECORD
