Metadata-Version: 2.1
Name: ruth-text-to-speech
Version: 0.0.39
Summary: A Python CLI for Ruth NLP
Home-page: 
Author: Puretalk
Author-email: info@puretalk.ai
Classifier: Development Status :: 3 - Alpha
Classifier: Intended Audience :: Developers
Classifier: Topic :: Software Development :: Build Tools
Classifier: Programming Language :: Python :: 3.8
Requires-Python: >=3.7,<3.9
Requires-Dist: tqdm
Requires-Dist: rotary-embedding-torch
Requires-Dist: inflect
Requires-Dist: progressbar
Requires-Dist: einops
Requires-Dist: unidecode
Requires-Dist: scipy
Requires-Dist: librosa
Requires-Dist: transformers
Requires-Dist: tokenizers
